VirtoAI/__init__.py
VirtoAI/bot.py
VirtoAI/cli.py
VirtoAI-59.84.8.dist-info/LICENCE
VirtoAI-59.84.8.dist-info/METADATA
VirtoAI-59.84.8.dist-info/WHEEL
VirtoAI-59.84.8.dist-info/entry_points.txt
VirtoAI-59.84.8.dist-info/top_level.txt
VirtoAI-59.84.8.dist-info/RECORD
