Metadata-Version: 2.1
Name: VirtoAI
Version: 59.84.8
Summary: Next Gen AI Bot
Home-page: https://github.com/Virtosync/VirtoAI
Author: Zack Allen
License: MIT
Keywords: AI,Bot,GPT
Classifier: Programming Language :: Python :: 3
Classifier: License :: OSI Approved :: MIT License
Classifier: Operating System :: OS Independent
License-File: LICENCE
Requires-Dist: nltk
Requires-Dist: textblob
Requires-Dist: click
Requires-Dist: requests
Requires-Dist: setuptools
Requires-Dist: cryptography
